LICENSE
MANIFEST.in
README.md
binding.cpp
core.cu
core.h
requirements.txt
setup.py
warp_rna/__init__.py
warp_rna/test.py
warp_rna.egg-info/PKG-INFO
warp_rna.egg-info/SOURCES.txt
warp_rna.egg-info/dependency_links.txt
warp_rna.egg-info/requires.txt
warp_rna.egg-info/top_level.txt